pydefer/__init__.py
pydefer/defer.py
pydefer-0.0.2.dist-info/LICENSE
pydefer-0.0.2.dist-info/METADATA
pydefer-0.0.2.dist-info/WHEEL
pydefer-0.0.2.dist-info/top_level.txt
pydefer-0.0.2.dist-info/RECORD
