Metadata-Version: 2.1
Name: pydefer
Version: 0.0.2
Summary: Implements a Go-like defer function.
Home-page: https://github.com/ssyuen/pydefer
Author: Samuel Yuen
Author-email: samuel.s.yuen@gmail.com
License: UNKNOWN
Platform: UNKNOWN
Classifier: Programming Language :: Python :: 3
Classifier: License :: OSI Approved :: MIT License
Classifier: Operating System :: OS Independent
Requires-Python: >=3.7
